sped/__init__.py
sped/arquivos.py
sped/blocos.py
sped/campos.py
sped/erros.py
sped/escrituracao.py
sped/leiaute.py
sped/registros.py
sped/ecd/__init__.py
sped/ecd/arquivos.py
sped/ecd/blocos.py
sped/ecd/registros.py
sped/ecd/tabelas.py
sped/ecf/__init__.py
sped/ecf/arquivos.py
sped/ecf/blocos.py
sped/ecf/registros.py
sped/efd/__init__.py
sped/efd/icms_ipi/__init__.py
sped/efd/icms_ipi/arquivos.py
sped/efd/icms_ipi/blocos.py
sped/efd/icms_ipi/registros.py
sped/efd/pis_cofins/__init__.py
sped/efd/pis_cofins/arquivos.py
sped/efd/pis_cofins/blocos.py
sped/efd/pis_cofins/registros.py
sped/fci/__init__.py
sped/fci/arquivos.py
sped/fci/blocos.py
sped/fci/registros.py
sped/leiautes/ecd_2016.json
sped/leiautes/ecd_2017.json
sped/leiautes/ecf_2016.json
sped/leiautes/ecf_2017.json
python_sped-1.1.4.dist-info/LICENSE
python_sped-1.1.4.dist-info/METADATA
python_sped-1.1.4.dist-info/WHEEL
python_sped-1.1.4.dist-info/top_level.txt
python_sped-1.1.4.dist-info/RECORD
